BubbleGun/Bubble.py
BubbleGun/BubbleChain.py
BubbleGun/Graph.py
BubbleGun/Node.py
BubbleGun/__init__.py
BubbleGun/__version__.py
BubbleGun/bfs.py
BubbleGun/bubbles_fasta.py
BubbleGun/compact_graph.py
BubbleGun/connect_bubbles.py
BubbleGun/connected_components.py
BubbleGun/fasta_chains.py
BubbleGun/find_bubbles.py
BubbleGun/find_parents.py
BubbleGun/functions.py
BubbleGun/graph_io.py
BubbleGun/json_out.py
BubbleGun/main.py
BubbleGun/output_certain_chains.py
BubbleGun/path_extractor.py
BubbleGun-1.1.9.dist-info/LICENSE
BubbleGun-1.1.9.dist-info/METADATA
BubbleGun-1.1.9.dist-info/WHEEL
BubbleGun-1.1.9.dist-info/entry_points.txt
BubbleGun-1.1.9.dist-info/top_level.txt
BubbleGun-1.1.9.dist-info/RECORD
