Metadata-Version: 2.1
Name: BubbleGun
Version: 1.1.9
Summary: Detection of Bubble and Superbubble chains in genome graphs
Home-page: https://github.com/fawaz-dabbaghieh/bubble_gun
Author: Fawaz Dabbaghie
Author-email: fawaz.dabbaghieh@gmail.com
License: LICENSE.TXT
License-File: LICENSE
